{"flavor": ["caramel", "toffee", "bready", "biscuity", "nutty", "roasted", "chocolate", "coffee", "mocha", "molasses", "syrupy", "smokey", "toasted", "vanilla", "cocoa", "sugar", "hoppy", "citrusy", "tropical", "floral", "piney", "herbal", "grassy", "earthy", "dank", "spicy", "peppery", "juicy", "zesty", "tangy", "bitterness", "estery", "fruity", "berry", " cherry", " apple", " banana", "pear", "stone fruit", "plum", "fig", "raisin", "peach", " apricot", "dark fruit", "citrus zest", "lemon", "peel", "orange", "pineapple", "mango", "lychee", "oaky", "woody", "bourbon", "whiskey", "rye", "tequila", "brandy", "vinous", "tart", "lacto", "honey", "clove", "bubblegum", "funky", "currant", "grape", "tea", "blueberry", "blackberry", "cassis", "gooseberry", "loganberry", "nectar", "nectarine", "pomegranate", "quince", "rasberry", "strawberry", "watermelon", "grapefruit", "lemongrass", "lime", "mandarin", "tangerine", "coconut", "cream", "guava", "melon", "papaya", "rose", "cedar", "cognac", "hay", "tobacco", "mint", "sage", "thyme", "aniseed", "cinnamon", "ginger", "pepper", "licorice", "candy", "cucumber", "garlic", "bouquet", "aromatic", "fragrant", "perfumed", "faint", "musky", "subtle", "yeasty", "malty", "pungent", "burnt"], "mouthfeel": ["body", "full-bodied", "medium-bodied", "light-bodied", "unfolding", "aftertaste", "thick", "thin", "creamy", "smooth", "velvety", "oily", "tannic", "chalky", "drying", "slick", "watery", "effervescent", "fizzy", "tingly", "prickly", "carbonated", "viscosity", "warming", "coating", "biting", "sharp", "rusty", "evolving"], "brewing": ["wheat", "dry", "hopping", "barrel", "conditioned", "fermentation", "wort", "mash", "sparging", "crashing", "decoction", "conditioning", "strain", "adjuncts", "grains", "malt"], "technical": ["balance", "palate", "complexity", "depth", "layers", "nuanced", "refined", "structured", "profile", "round", "harmonious", "clean", "crisp", "finish", "lingering", "evolving", "clarity", "purity", "dense", "robust", "powerful", "restrained", "vibrant", "subdued", "heavy", "integrity", "layered", "benchmark", "classic", "signature", "finesse", "elegance", "exemplar", "well-integrated", "classic example", "flawless", "exceptional", "outstanding", "world-class", "traditional", "innovative", "unconventional", "unique"], "appearance": ["hazy", "cloudy", "opaque", "translucent", "clear", "bright", "unfiltered", "filtered", "lacing", "foam", "frothy", "rocky head", "stable head", "gold", "amber", "ruby", "copper", "dark", "black", "mahogany", "light", "straw", "yellow", "chestnut", "tan", "off-white", "blonde", "bronze", "coal", "ebony", "inky", "milky", "muddy", "obsidian", "sepia", "sunlight", "transparent"], "off_flavors": ["rotten", "sulphur", "egg", "goat", "sour", "tasteless", "inferior", "acidic", "oxidized", "piss", "metallic", "cardboard", "stale", "sulfur", "skunky", "diacetyl", "astringent", "phenolic", "acetaldehyde", "DMS", "cloying", "solvent-like", "overly bitter", "thin", "harsh", "vegetal", "buttery", "musty, moldy", "medicinal"]}